swifttools/__init__.py
swifttools/version.py
swifttools/swift_too/ChangeLog.md
swifttools/swift_too/README.md
swifttools/swift_too/__init__.py
swifttools/swift_too/api_common.py
swifttools/swift_too/api_daterange.py
swifttools/swift_too/api_resolve.py
swifttools/swift_too/api_skycoord.py
swifttools/swift_too/api_status.py
swifttools/swift_too/query_job.py
swifttools/swift_too/swift_calendar.py
swifttools/swift_too/swift_clock.py
swifttools/swift_too/swift_data.py
swifttools/swift_too/swift_guano.py
swifttools/swift_too/swift_instruments.py
swifttools/swift_too/swift_obsid.py
swifttools/swift_too/swift_obsquery.py
swifttools/swift_too/swift_planquery.py
swifttools/swift_too/swift_requests.py
swifttools/swift_too/swift_saa.py
swifttools/swift_too/swift_toorequest.py
swifttools/swift_too/swift_uvot.py
swifttools/swift_too/swift_visquery.py
swifttools/swift_too/version.py
swifttools/ukssdc/__init__.py
swifttools/ukssdc/main.py
swifttools/ukssdc/version.py
swifttools/ukssdc/APIDocs/ukssdc/ChangeLog.md
swifttools/ukssdc/APIDocs/ukssdc/README.md
swifttools/ukssdc/APIDocs/ukssdc/commonFunc.md
swifttools/ukssdc/APIDocs/ukssdc/data.ipynb
swifttools/ukssdc/APIDocs/ukssdc/data.md
swifttools/ukssdc/APIDocs/ukssdc/query.ipynb
swifttools/ukssdc/APIDocs/ukssdc/query.md
swifttools/ukssdc/APIDocs/ukssdc/structures.md
swifttools/ukssdc/APIDocs/ukssdc/test.md
swifttools/ukssdc/APIDocs/ukssdc/xrt_prods.md
swifttools/ukssdc/APIDocs/ukssdc/data/GRB.ipynb
swifttools/ukssdc/APIDocs/ukssdc/data/GRB.md
swifttools/ukssdc/APIDocs/ukssdc/data/GRBLC.png
swifttools/ukssdc/APIDocs/ukssdc/data/SXPS.ipynb
swifttools/ukssdc/APIDocs/ukssdc/data/SXPS.md
swifttools/ukssdc/APIDocs/ukssdc/data/SXPS_LC1.png
swifttools/ukssdc/APIDocs/ukssdc/data/SXPS_LC2.png
swifttools/ukssdc/APIDocs/ukssdc/query/GRB.ipynb
swifttools/ukssdc/APIDocs/ukssdc/query/GRB.md
swifttools/ukssdc/APIDocs/ukssdc/query/GRB_1.png
swifttools/ukssdc/APIDocs/ukssdc/query/GRB_2.png
swifttools/ukssdc/APIDocs/ukssdc/query/GRB_3.png
swifttools-3.0.24.dist-info/licenses/LICENSE
swifttools-3.0.24.dist-info/METADATA
swifttools-3.0.24.dist-info/WHEEL
swifttools-3.0.24.dist-info/top_level.txt
swifttools-3.0.24.dist-info/RECORD
