Metadata-Version: 2.4
Name: swifttools
Version: 3.0.24
Summary: Tools for users of the Swift satellite
Home-page: https://github.com/Swift-SOT/swifttools
Author: Phil A. Evans
Author-email: pae9@leicester.ac.uk
Classifier: Development Status :: 5 - Production/Stable
Classifier: Intended Audience :: Science/Research
Classifier: License :: OSI Approved :: MIT License
Classifier: Operating System :: OS Independent
Classifier: Programming Language :: Python :: 3
Classifier: Programming Language :: Python :: 3 :: Only
Classifier: Programming Language :: Python :: 3.6
Classifier: Programming Language :: Python :: Implementation :: CPython
Classifier: Topic :: Scientific/Engineering :: Astronomy
Classifier: Topic :: Scientific/Engineering :: Physics
Classifier: Natural Language :: English
Requires-Python: >=3.6
License-File: LICENSE
Requires-Dist: requests
Requires-Dist: PyJWT
Requires-Dist: pandas
Requires-Dist: tabulate
Requires-Dist: numpy
Requires-Dist: boto3
Dynamic: license-file
